tftool/__init__.py
tftool/__main__.py
tftool/_backport.py
tftool/py.typed
tftool-0.0.4.dist-info/LICENSE
tftool-0.0.4.dist-info/METADATA
tftool-0.0.4.dist-info/WHEEL
tftool-0.0.4.dist-info/entry_points.txt
tftool-0.0.4.dist-info/top_level.txt
tftool-0.0.4.dist-info/RECORD
