Metadata-Version: 2.1
Name: tftool
Version: 0.0.4
Summary: Ergonomic utilities for the terraform CLI.
Home-page: UNKNOWN
Author: Barnaby Shearer
Author-email: b@zi.is
License: UNKNOWN
Project-URL: Source, https://github.com/BarnabyShearer/tftool
Project-URL: Tracker, https://github.com/BarnabyShearer/tftool/issues
Project-URL: Documentation, https://tftool.readthedocs.io/en/latest/
Project-URL: Docker, https://hub.docker.com/repository/docker/barnabyshearer/tftool
Keywords: terraform
Platform: UNKNOWN
Classifier: Development Status :: 5 - Production/Stable
Classifier: Programming Language :: Python :: 3
Requires-Python: >=3.7
License-File: LICENSE
